Progra_DIGI/FSM.v
// Luis Pedro Molina Velásquez - Carné 18822
// Electrónica Digital 1 - Sección 12
// Proyecto 1 - Máquinas de Estados Finitos

// Máquina seleccionadora de menú con dispensador de bebida incluido

// FlipFlop tipo D de 3 bits

module FlipFloptipoD3Bits(input wire [2:0] D, input wire clk, input wire reset, output [2:0] Q);
reg Q;
    always @(posedge clk or posedge reset)
        if(reset)
            Q <= 3'b000;
    else begin
            Q <= D; 
    end
    
endmodule

// Timer 1 

module Timer (input wire ENABLE, output reg TIME);
    always @ (ENABLE) begin
        if (ENABLE == 0) begin
            TIME = 0;
        end while(ENABLE) begin
            TIME = 0;
            #5 TIME = 1;
            #5 TIME = 0;
        end
        
    end
endmodule

module FSM_BIENVENIDA (input wire clk, reset, output wire [2:0]F, output wire [2:0]A, input wire ON, input wire CONT, input wire TIME, input wire [1:0]SELE, output wire [2:0]DISP, output wire [2:0]MENU, output wire ENABLE);

    FlipFloptipoD3Bits U1(F, clk, reset, A); 

// INTERFAZ DE BIENVENIDA - SELECCIÓN DE MENÚS 

    assign F[2]    = (~A[2] & A[1] & ~A[0] & SELE[1]) | (~A[2] & A[1] & ~A[0] & SELE[0]);
    assign F[1]    = (~A[2] & ~A[1] & A[0] & CONT) | (~A[2] & A[1] & ~A[0] & SELE[1] & SELE[0]) | (~A[2] & A[1] & ~A[0] & ~SELE[1] & ~SELE[0]);
    assign F[0]    = (~A[2] & ~A[1] & ~A[0] & ON) | (~A[2] & ~A[1] & A[0] & ~CONT & ~TIME) | (~A[2] & A[1] & ~A[0] & SELE[1] & ~SELE[0]);
    assign MENU[2] = (A[2] & ~A[1] & ~A[0]);
    assign MENU[1] = (A[2] & ~A[1] & A[0]);
    assign MENU[0] = (A[2] & A[1] & ~A[0]);
    assign DISP[2] = (A[2] & ~A[1]) | (A[2] & ~A[0]);
    assign DISP[1] = (A[2] & A[1] & ~A[0]);
    assign DISP[0] = (A[2] & ~A[1] & A[0]);
    assign ENABLE  = (~A[2] & ~A[1] & A[0]);

endmodule

module FSM_MENU1 (input wire clk, reset, output wire [2:0]F, output wire [2:0]A, input wire [2:0]MENU, input wire CONT, input wire TIME, input wire [2:0]SELE, output wire [2:0]DISP, output wire [3:0]OP, output wire ENABLE);

    DFlipFlop3bits U2 (F, clk, reset, A);

// INTERFAZ DE MENÚ 1 - PLATOS FUERTES

    assign F[2]    = (~A[2] & A[1] & ~A[0] & ~SELE[2] & SELE[1]) | (~A[2] & A[1] & ~A[0] & SELE[2] & ~SELE[1] & ~SELE[0]);
    assign F[1]    = (~A[2] & ~A[1] & A[0] & CONT) | (~A[2] & A[1] & ~A[0] & ~SELE[1]) | (~A[2] & A[1] & ~A[0] & SELE[2] & ~SELE[0]);
    assign F[0]    = (~A[2] & ~A[1] & ~A[0] & ON) | (~A[2] & ~A[1] & A[0] & ~CONT & ~TIME) | (~A[2] & A[1] & ~A[0] & ~SELE[2] & SELE[0]) | (~A[2] & A[1] & ~A[0] & SELE[1] & SELE[0]);
    assign OP[3]   = (~A[2] & A[1] & A[0]);
    assign OP[2]   = (A[2] & ~A[1] & ~A[0]);
    assign OP[1]   = (A[2] & ~A[1] & A[0]);
    assign OP[0]   = (A[2] & A[1] & ~A[0]);
    assign DISP[3] = (~A[2] & A[1] & A[0]);
    assign DISP[2] = (A[2] & ~A[1] & ~A[0]);
    assign DISP[1] = (A[2] & ~A[1] & A[0]);
    assign DISP[0] = (A[2] & A[1] & ~A[0]);
    assign ENABLE  = (~A[2] & ~A[1] & A[0]);


endmodule

/*module FMS_MENU2 (input wire clk, reset, input wire [2:0]F, input wire [2:0]A, input wire CONT, TIME, [2:0]SELE, output wire [3:0]DISP, [3:0]G);

    DFlipFlop3bits U3 (F, clk, reset, A);

// INTERFAZ DE MENÚ 2 - GUARNICIONES

    assign F[2]    = (~A[2] & A[1] & ~A[0] & ~SELE[2] & SELE[1]) | (~A[2] & A[1] & ~A[0] & SELE[2] & ~SELE[1] & ~SELE[0]);
    assign F[1]    = (~A[2] & ~A[1] & A[0] & CONT) | (~A[2] & A[1] & ~A[0] & ~SELE[1]) | (~A[2] & A[1] & ~A[0] & SELE[2] & ~SELE[0]);
    assign F[0]    = (~A[2] & ~A[1] & ~A[0] & ON) | (~A[2] & ~A[1] & A[0] & ~CONT & ~TIME) | (~A[2] & A[1] & ~A[0] & ~SELE[2] & SELE[0]) | (~A[2] & A[1] & ~A[0] & SELE[1] & SELE[0]);
    assign G[3]    = (~A[2] & A[1] & A[0]);
    assign G[2]    = (A[2] & ~A[1] & ~A[0]);
    assign G[1]    = (A[2] & ~A[1] & A[0]);
    assign G[0]    = (A[2] & A[1] & ~A[0]);
    assign DISP[3] = (~A[2] & A[1] & A[0]);
    assign DISP[2] = (A[2] & ~A[1] & ~A[0]);
    assign DISP[1] = (A[2] & ~A[1] & A[0]);
    assign DISP[0] = (A[2] & A[1] & ~A[0]);
    assign ENABLE  = (~A[2] & ~A[1] & A[0]);

endmodule

module FMS_MENU3 (input wire clk, reset, input wire [2:0]F, input wire [2:0]A, input wire CONT, TIME, [2:0]SELE, output wire [3:0]DISP, [3:0]B);

    DFlipFlop3bits U4 (F, clk, reset, A);
    
// INTERFAZ DE MENÚ 3 - BEBIDAS

    assign F[2]    = (~A[2] & A[1] & ~A[0] & ~SELE[2] & SELE[1]) | (~A[2] & A[1] & ~A[0] & SELE[2] & ~SELE[1] & ~SELE[0]);
    assign F[1]    = (~A[2] & ~A[1] & A[0] & CONT) | (~A[2] & A[1] & ~A[0] & ~SELE[1]) | (~A[2] & A[1] & ~A[0] & SELE[2] & ~SELE[0]);
    assign F[0]    = (~A[2] & ~A[1] & ~A[0] & ON) | (~A[2] & ~A[1] & A[0] & ~CONT & ~TIME) | (~A[2] & A[1] & ~A[0] & ~SELE[2] & SELE[0]) | (~A[2] & A[1] & ~A[0] & SELE[1] & SELE[0]);
    assign B[3]    = (~A[2] & A[1] & A[0]);
    assign B[2]    = (A[2] & ~A[1] & ~A[0]);
    assign B[1]    = (A[2] & ~A[1] & A[0]);
    assign B[0]    = (A[2] & A[1] & ~A[0]);
    assign DISP[3] = (~A[2] & A[1] & A[0]);
    assign DISP[2] = (A[2] & ~A[1] & ~A[0]);
    assign DISP[1] = (A[2] & ~A[1] & A[0]);
    assign DISP[0] = (A[2] & A[1] & ~A[0]);
    assign ENABLE  = (~A[2] & ~A[1] & A[0]);

endmodule
*/

Progra_DIGI/FSM_tb.v
// Luis Pedro Molina Velásquez - Carné 18822
// Electrónica Digital 1 - Sección 12
// Proyecto 1 - Máquinas de Estados Finitos

// Máquina seleccionadora de menú con dispensador de bebida incluido

// TESTBENCH

module testbench();

reg clk, reset, set,  ON, CONT; 
reg [1:0]SELE;
wire TIME;
wire [2:0]A;
wire [2:0]F;
wire [2:0]DISP;
wire [2:0]MENU;
wire ENABLE;

FSM_BIENVENIDA FSM(clk, reset, F, A, ON, CONT, TIME, SELE, DISP, MENU, ENABLE);
Timer TIM(ENABLE, TIME);
initial begin
    clk=1;
    forever #5 clk = ~clk;
end

    initial begin
    
        #1 
        $display (" ");
        $display(" Proyecto 1 - FSM");
        $display("    A     ON    CONT   TIME    SELE | F      MENU     DISP   ENABLE ");
        $display(" --------------------------------| ---------------------------- ");
        $monitor(" %b    %b      %b      %b       %b | %b     %b     %b      %b  ", A, ON, CONT, TIME, SELE, F, MENU, DISP, ENABLE);

            reset = 0 ; ON = 0 ; CONT = 0; SELE = 2'b00; 
        #1  reset = 1 ;
        #1  reset = 0 ; 

        // Prueba de que la Interfaz de Bienvenida (Seleccionador de menús) solo se activa con "ON = 1"
        #7   ON = 0 ; CONT = 0 ; SELE = 2'b00 ; 
        #10  ON = 0 ; CONT = 1 ; SELE = 2'b00 ; 
        #10  ON = 0 ; CONT = 0 ; SELE = 2'b01 ; 
        #10  ON = 0 ; CONT = 0 ; SELE = 2'b10 ;  
        #10  ON = 1 ; CONT = 0 ; SELE = 2'b00 ;
        #10  ON = 0 ; CONT = 0 ; SELE = 2'b11 ;    

        #5  reset = 1 ;
        #5  reset = 0 ;

        // Prueba de que el timer funciona correctamente.

        #0   ON = 1 ; CONT = 0 ; SELE = 2'b00 ;
        #10  ON = 0 ; CONT = 0 ; SELE = 2'b01 ;
        #10  ON = 0 ; CONT = 0 ; SELE = 2'b11 ;

        #5  reset = 1 ;
        #5  reset = 0 ; 
        
        // Probando elección de Menú 1 - Platos Fuertes
        #0   ON = 1 ; CONT = 0 ; SELE = 2'b00 ;
        #10  ON = 0 ; CONT = 1 ; SELE = 2'b00 ;
        #10  ON = 0 ; CONT = 0 ; SELE = 2'b01 ;
        #10  ON = 0 ; CONT = 0 ; SELE = 2'b00 ; 
    
        #5  reset = 1 ;
        #5  reset = 0 ;

        // Probando elección de Menú 2 - Guarniciones 
        #0   ON = 1 ; CONT = 0 ; SELE = 2'b00 ;
        #10  ON = 0 ; CONT = 1 ; SELE = 2'b00 ;
        #10  ON = 0 ; CONT = 0 ; SELE = 2'b10 ;
        #10  ON = 0 ; CONT = 0 ; SELE = 2'b00 ; 

        #5  reset = 1 ;
        #5  reset = 0 ;

        // Probando elección de Menú 3 - Bebidas
        #0   ON = 1 ; CONT = 0 ; SELE = 2'b00 ;
        #10  ON = 0 ; CONT = 1 ; SELE = 2'b00 ;
        #10  ON = 0 ; CONT = 0 ; SELE = 2'b11 ;
        #10  ON = 0 ; CONT = 0 ; SELE = 2'b00 ; 

        #5  reset = 1 ;
        #5  reset = 0 ;





        // Prueba de transción a Menú 1 - Platos Fuertes

       /* #10  ON = 1 ; CONT = 0 ; SELE = 2'b00 ;
        #10  ON = 0 ; CONT = 1 ; SELE = 2'b00 ;
        #10  ON = 0 ; CONT = 0 ; SELE = 2'b01 ;
/*
        // Prueba de transición a Menú 2 - Guarniciones
        #10 ON = 1 ; CONT = 0 ; SELE = 2'b00 ; 
        #10 ON = 0 ; CONT = 1 ; SELE = 2'b00 ;
        #10 ON = 0 ; CONT = 0 ; SELE = 2'b10 ;

        // Prueba de transición a Menú 3 - Bebidas
        #10 ON = 1 ; CONT = 0 ; SELE = 2'b00 ;
        #10 ON = 0 ; CONT = 1 ; SELE = 2'b00 ;
        #10 ON = 0 ; CONT = 1 ; SELE = 2'b11 ; 

        
        #16  ON = 0 ; CONT = 1 ; TIME = 0 ; SELE = 2'b00 ;
        #26  ON = 0 ; CONT = 0 ; TIME = 1 ; SELE = 2'b00 ;
        #36  ON = 0 ; CONT = 0 ; TIME = 0 ; SELE = 2'b00 ;
        #46  ON = 0 ; CONT = 0 ; TIME = 0 ; SELE = 2'b01 ;
        #56  ON = 0 ; CONT = 0 ; TIME = 0 ; SELE = 2'b10 ;
        #66  ON = 0 ; CONT = 0 ; TIME = 0 ; SELE = 2'b11 ;

        // Prueba de que el timer funciona, regresa de S0 a SR si "CONT = 0" y "TIME = 1" 
        #76  ON = 0 ; CONT = 0 ; TIME = 0 ; SELE = 2'b00 ;  // S0
        #86  ON = 0 ; CONT = 0 ; TIME = 1 ; SELE = 2'b00 ;  // SR

        // Probando selección de menú 1 - Platos fuertes
        #96  ON = 1 ; CONT = 0 ; TIME = 0 ; SELE = 2'b00 ; // S0 
        #106 ON = 0 ; CONT = 1 ; TIME = 0 ; SELE = 2'b00 ; // S1 
        #116 ON = 0 ; CONT = 0 ; TIME = 0 ; SELE = 2'b01 ; // S2 - Menú 1 y regresa a SR 

        // Probando selección de menú 2 - Guarniciones
        #126 ON = 1 ; CONT = 0 ; TIME = 0 ; SELE = 2'b00; // S0
        #136 ON = 0 ; CONT = 1 ; TIME = 0 ; SELE = 2'b00; // S1
        #146 ON = 0 ; CONT = 0 ; TIME = 0 ; SELE = 2'b10; // S2 - Menú 2
        
        // Probando selección de menú 3 - Bebidas 
        #156 ON = 1 ; CONT = 0 ; TIME = 0 ; SELE = 2'b00; // S0
        #166 ON = 0 ; CONT = 1 ; TIME = 0 ; SELE = 2'b00; // S1
        #176 ON = 0 ; CONT = 0 ; TIME = 0 ; SELE = 2'b11; // S3 - Menú 3
*/





        /*
        #6  ON = 0 ; CONT = 0 ; SELE = 2'b01 ; // SR
        #6  ON = 0 ; CONT = 0 ; SELE = 2'b10 ; // SR
        #6  ON = 0 ; CONT = 0 ; SELE = 2'b11 ; // SR*/

/*
        // Prueba de que el timer funciona, regresa de S0 a SR si "CONT = 0" y "TIME = 1" 
        #6  ON = 1 ; CONT = 0 ; SELE = 2'b00 ; // S0
        #6  ON = 0 ; CONT = 0 ; SELE = 2'b00 ; // S0
        #6  ON = 0 ; CONT = 0 ; SELE = 2'b00 ; // SR

        // Probando selección de menú 1 - Platos fuertes
        #6 ON = 1 ; CONT = 0 ; SELE = 2'b00 ; // S0 
        #6 ON = 0 ; CONT = 1 ; SELE = 2'b00 ; // S1 
        #6 ON = 0 ; CONT = 0 ; SELE = 2'b01 ; // S2 - Menú 1 y regresa a SR 

        // Probando selección de menú 2 - Guarniciones
        #6 ON = 1 ; CONT = 0 ; SELE = 2'b00; // S0
        #6 ON = 0 ; CONT = 1 ; SELE = 2'b00; // S1
        #6 ON = 0 ; CONT = 0 ; SELE = 2'b10; // S2 - Menú 2
        
        // Probando selección de menú 3 - Bebidas 
        #6 ON = 1 ; CONT = 0 ; SELE = 2'b00; // S0
        #6 ON = 0 ; CONT = 1 ; SELE = 2'b00; // S1
        #6 ON = 0 ; CONT = 0 ; SELE = 2'b11; // S3 - Menú 3

*/
    end

    initial
    #250  $finish;

initial
    begin
        $dumpfile("FSM_tb.vcd");
        $dumpvars(0, testbench);
    end
endmodule

Progra_DIGI/FSM_tb.vcd
$date
	Sun Oct 11 22:12:38 2020
$end
$version
	Icarus Verilog
$end
$timescale
	1ps
$end
$scope module testbench $end
$var wire 1 ! TIME $end
$var wire 3 " MENU [2:0] $end
$var wire 3 # F [2:0] $end
$var wire 1 $ ENABLE $end
$var wire 3 % DISP [2:0] $end
$var wire 3 & A [2:0] $end
$var reg 1 ' CONT $end
$var reg 1 ( ON $end
$var reg 2 ) SELE [1:0] $end
$var reg 1 * clk $end
$var reg 1 + reset $end
$scope module FSM $end
$var wire 1 ' CONT $end
$var wire 1 $ ENABLE $end
$var wire 1 ( ON $end
$var wire 2 , SELE [1:0] $end
$var wire 1 * clk $end
$var wire 1 + reset $end
$var wire 1 ! TIME $end
$var wire 3 - MENU [2:0] $end
$var wire 3 . F [2:0] $end
$var wire 3 / DISP [2:0] $end
$var wire 3 0 A [2:0] $end
$scope module U1 $end
$var wire 3 1 D [2:0] $end
$var wire 1 * clk $end
$var wire 1 + reset $end
$var reg 3 2 Q [2:0] $end
$upscope $end
$upscope $end
$scope module TIM $end
$var wire 1 $ ENABLE $end
$var reg 1 ! TIME $end
$upscope $end
$upscope $end
$enddefinitions $end
#0
$dumpvars
bx 2
bx 1
bx 0
bx /
bx .
bx -
bx ,
x+
1*
bx )
x(
x'
bx &
bx %
x$
bx #
bx "
x!
$end
#1
b0xx #
b0xx .
b0xx 1
b0 )
b0 ,
0'
0(
0+
#2
b0 #
b0 .
b0 1
0!
0$
b0 %
b0 /
b0 "
b0 -
b0 &
b0 0
b0 2
1+
#3
0+
#5
0*
#10
1*
#15
0*
#20
1*
1'
#25
0*
#30
1*
b1 )
b1 ,
0'
#35
0*
#40
1*
b10 )
b10 ,
#45
0*
#50
b1 #
b1 .
b1 1
1*
b0 )
b0 ,
1(
#55
0*
#60
1$
b1 &
b1 0
b1 2
b1 #
b1 .
b1 1
1*
b11 )
b11 ,
0(
#65
0$
b0 &
b0 0
b0 2
b0 #
b0 .
b0 1
1!
0*
1+
#70
b1 #
b1 .
b1 1
b0 )
b0 ,
1(
0!
1*
0+
#75
0*
#80
1$
b1 &
b1 0
b1 2
b1 #
b1 .
b1 1
1*
b1 )
b1 ,
0(
#85
b0 #
b0 .
b0 1
1!
0*
#90
0$
b0 &
b0 0
b0 2
b0 #
b0 .
b0 1
0!
1*
b11 )
b11 ,
#95
1!
0*
1+
#100
b1 #
b1 .
b1 1
b0 )
b0 ,
1(
0!
1*
0+
#105
0*
#110
1$
b1 &
b1 0
b1 2
b10 #
b10 .
b10 1
1*
1'
0(
#115
1!
0*
#120
0$
b10 &
b10 0
b10 2
b100 #
b100 .
b100 1
0!
1*
b1 )
b1 ,
0'
#125
1!
0*
#130
b100 "
b100 -
b100 %
b100 /
b100 &
b100 0
b100 2
b0 #
b0 .
b0 1
0!
1*
b0 )
b0 ,
#135
b0 %
b0 /
b0 "
b0 -
b0 &
b0 0
b0 2
0*
1+
#140
b1 #
b1 .
b1 1
1(
1*
0+
#145
0*
#150
1$
b1 &
b1 0
b1 2
b10 #
b10 .
b10 1
1*
1'
0(
#155
1!
0*
#160
0$
b10 &
b10 0
b10 2
b101 #
b101 .
b101 1
0!
1*
b10 )
b10 ,
0'
#165
1!
0*
#170
b10 "
b10 -
b101 %
b101 /
b101 &
b101 0
b101 2
b0 #
b0 .
b0 1
0!
1*
b0 )
b0 ,
#175
b0 %
b0 /
b0 "
b0 -
b0 &
b0 0
b0 2
0*
1+
#180
b1 #
b1 .
b1 1
1(
1*
0+
#185
0*
#190
1$
b1 &
b1 0
b1 2
b10 #
b10 .
b10 1
1*
1'
0(
#195
1!
0*
#200
0$
b10 &
b10 0
b10 2
b110 #
b110 .
b110 1
0!
1*
b11 )
b11 ,
0'
#205
1!
0*
#210
b110 %
b110 /
b1 "
b1 -
b110 &
b110 0
b110 2
b0 #
b0 .
b0 1
0!
1*
b0 )
b0 ,
#215
b0 %
b0 /
b0 "
b0 -
b0 &
b0 0
b0 2
0*
1+
#220
1*
0+
